<?xml version="1.0" encoding="utf-8"?>
<ABCfg xmlns:xsd="http://www.w3.org/2001/XMLSchema" xmlns:xsi="http://www.w3.org/2001/XMLSchema-instance">
  <ABLst>
    <Path>Assets/GameData/Prefabs/Attack.prefab</Path>
    <Crc>1330568117</Crc>
    <ABName>attack</ABName>
    <AssetName>Assets/GameData/Prefabs/Attack.prefab</AssetName>
  </ABLst>
  <ABLst>
    <Path>Assets/GameData/Prefabs/Cube.prefab</Path>
    <Crc>3768865536</Crc>
    <ABName>cube</ABName>
    <AssetName>Assets/GameData/Prefabs/Cube.prefab</AssetName>
  </ABLst>
  <ABLst>
    <Path>Assets/GameData/Prefabs/UGUI/Panel/Demo13/Demo13MenuPanel.prefab</Path>
    <Crc>2510388767</Crc>
    <ABName>demo13menupanel</ABName>
    <AssetName>Assets/GameData/Prefabs/UGUI/Panel/Demo13/Demo13MenuPanel.prefab</AssetName>
  </ABLst>
  <ABLst>
    <Path>Assets/GameData/Prefabs/UGUI/Panel/Demo14/Demo14LoadPanel.prefab</Path>
    <Crc>2412948903</Crc>
    <ABName>demo14loadpanel</ABName>
    <AssetName>Assets/GameData/Prefabs/UGUI/Panel/Demo14/Demo14LoadPanel.prefab</AssetName>
  </ABLst>
  <ABLst>
    <Path>Assets/GameData/Prefabs/UGUI/Panel/Demo14/Demo14MenuPanel.prefab</Path>
    <Crc>1461134629</Crc>
    <ABName>demo14menupanel</ABName>
    <AssetName>Assets/GameData/Prefabs/UGUI/Panel/Demo14/Demo14MenuPanel.prefab</AssetName>
  </ABLst>
  <ABLst>
    <Path>Assets/GameData/Images/fgBlue.png</Path>
    <Crc>1064515496</Crc>
    <ABName>image</ABName>
    <AssetName>Assets/GameData/Images/fgBlue.png</AssetName>
  </ABLst>
  <ABLst>
    <Path>Assets/GameData/Images/fgGray.png</Path>
    <Crc>79892824</Crc>
    <ABName>image</ABName>
    <AssetName>Assets/GameData/Images/fgGray.png</AssetName>
  </ABLst>
  <ABLst>
    <Path>Assets/GameData/Images/fgGreen.png</Path>
    <Crc>248452608</Crc>
    <ABName>image</ABName>
    <AssetName>Assets/GameData/Images/fgGreen.png</AssetName>
  </ABLst>
  <ABLst>
    <Path>Assets/GameData/Images/fgPurple.png</Path>
    <Crc>1982286351</Crc>
    <ABName>image</ABName>
    <AssetName>Assets/GameData/Images/fgPurple.png</AssetName>
  </ABLst>
  <ABLst>
    <Path>Assets/GameData/Images/fgRed.png</Path>
    <Crc>1196913882</Crc>
    <ABName>image</ABName>
    <AssetName>Assets/GameData/Images/fgRed.png</AssetName>
  </ABLst>
  <ABLst>
    <Path>Assets/GameData/Images/fgYellow.png</Path>
    <Crc>3443904232</Crc>
    <ABName>image</ABName>
    <AssetName>Assets/GameData/Images/fgYellow.png</AssetName>
  </ABLst>
  <ABLst>
    <Path>Assets/GameData/Shaders/benghuai.shader</Path>
    <Crc>1145813025</Crc>
    <ABName>shader</ABName>
    <AssetName>Assets/GameData/Shaders/benghuai.shader</AssetName>
  </ABLst>
  <ABLst>
    <Path>Assets/GameData/Shaders/Skybox.shader</Path>
    <Crc>1986987949</Crc>
    <ABName>shader</ABName>
    <AssetName>Assets/GameData/Shaders/Skybox.shader</AssetName>
  </ABLst>
  <ABLst>
    <Path>Assets/GameData/Shaders/Water.shader</Path>
    <Crc>1357101244</Crc>
    <ABName>shader</ABName>
    <AssetName>Assets/GameData/Shaders/Water.shader</AssetName>
  </ABLst>
  <ABLst>
    <Path>Assets/GameData/Shaders/Xray.shader</Path>
    <Crc>1043595403</Crc>
    <ABName>shader</ABName>
    <AssetName>Assets/GameData/Shaders/Xray.shader</AssetName>
  </ABLst>
  <ABLst>
    <Path>Assets/GameData/Sounds/menusound.mp3</Path>
    <Crc>2729331572</Crc>
    <ABName>sound</ABName>
    <AssetName>Assets/GameData/Sounds/menusound.mp3</AssetName>
  </ABLst>
  <ABLst>
    <Path>Assets/GameData/Sounds/senlin.mp3</Path>
    <Crc>3022988390</Crc>
    <ABName>sound</ABName>
    <AssetName>Assets/GameData/Sounds/senlin.mp3</AssetName>
  </ABLst>
</ABCfg>